{
  "last_updated_ts": 1767072754.927775,
  "hypotheses": [
    {
      "id": "hyp_1767071599_0",
      "created_ts": 1767071599.8227432,
      "pattern": "keep building",
      "evidence": [],
      "weight": 0.2,
      "validations": 0,
      "status": "pending_veto",
      "conditional": null,
      "category": "preference"
    },
    {
      "id": "hyp_1767071599_1",
      "created_ts": 1767071599.8227432,
      "pattern": "warm",
      "evidence": [],
      "weight": 0.2,
      "validations": 0,
      "status": "pending_veto",
      "conditional": null,
      "category": "preference"
    },
    {
      "id": "hyp_1767071599_2",
      "created_ts": 1767071599.8227432,
      "pattern": "helpful",
      "evidence": [],
      "weight": 0.2,
      "validations": 0,
      "status": "pending_veto",
      "conditional": null,
      "category": "preference"
    },
    {
      "id": "hyp_1767071599_3",
      "created_ts": 1767071599.8227432,
      "pattern": "gentle",
      "evidence": [],
      "weight": 0.2,
      "validations": 0,
      "status": "pending_veto",
      "conditional": null,
      "category": "preference"
    },
    {
      "id": "hyp_1767071599_4",
      "created_ts": 1767071599.8227432,
      "pattern": "steady",
      "evidence": [],
      "weight": 0.2,
      "validations": 0,
      "status": "pending_veto",
      "conditional": null,
      "category": "preference"
    },
    {
      "id": "hyp_1767071607_0",
      "created_ts": 1767071607.717733,
      "pattern": "keep building",
      "evidence": [],
      "weight": 0.2,
      "validations": 0,
      "status": "pending_veto",
      "conditional": null,
      "category": "preference"
    },
    {
      "id": "hyp_1767071607_1",
      "created_ts": 1767071607.717733,
      "pattern": "warm",
      "evidence": [],
      "weight": 0.2,
      "validations": 0,
      "status": "pending_veto",
      "conditional": null,
      "category": "preference"
    },
    {
      "id": "hyp_1767071607_2",
      "created_ts": 1767071607.717733,
      "pattern": "helpful",
      "evidence": [],
      "weight": 0.2,
      "validations": 0,
      "status": "pending_veto",
      "conditional": null,
      "category": "preference"
    },
    {
      "id": "hyp_1767071607_3",
      "created_ts": 1767071607.717733,
      "pattern": "gentle",
      "evidence": [],
      "weight": 0.2,
      "validations": 0,
      "status": "pending_veto",
      "conditional": null,
      "category": "preference"
    },
    {
      "id": "hyp_1767071607_4",
      "created_ts": 1767071607.717733,
      "pattern": "steady",
      "evidence": [],
      "weight": 0.2,
      "validations": 0,
      "status": "pending_veto",
      "conditional": null,
      "category": "preference"
    },
    {
      "id": "hyp_1767071608_0",
      "created_ts": 1767071608.7859695,
      "pattern": "keep building",
      "evidence": [],
      "weight": 0.2,
      "validations": 0,
      "status": "pending_veto",
      "conditional": null,
      "category": "preference"
    },
    {
      "id": "hyp_1767071608_1",
      "created_ts": 1767071608.7859695,
      "pattern": "warm",
      "evidence": [],
      "weight": 0.2,
      "validations": 0,
      "status": "pending_veto",
      "conditional": null,
      "category": "preference"
    },
    {
      "id": "hyp_1767071608_2",
      "created_ts": 1767071608.7859695,
      "pattern": "helpful",
      "evidence": [],
      "weight": 0.2,
      "validations": 0,
      "status": "pending_veto",
      "conditional": null,
      "category": "preference"
    },
    {
      "id": "hyp_1767071608_3",
      "created_ts": 1767071608.7859695,
      "pattern": "gentle",
      "evidence": [],
      "weight": 0.2,
      "validations": 0,
      "status": "pending_veto",
      "conditional": null,
      "category": "preference"
    },
    {
      "id": "hyp_1767071608_4",
      "created_ts": 1767071608.7859695,
      "pattern": "steady",
      "evidence": [],
      "weight": 0.2,
      "validations": 0,
      "status": "pending_veto",
      "conditional": null,
      "category": "preference"
    },
    {
      "id": "hyp_1767071609_0",
      "created_ts": 1767071609.826809,
      "pattern": "keep building",
      "evidence": [],
      "weight": 0.2,
      "validations": 0,
      "status": "pending_veto",
      "conditional": null,
      "category": "preference"
    },
    {
      "id": "hyp_1767071609_1",
      "created_ts": 1767071609.826809,
      "pattern": "warm",
      "evidence": [],
      "weight": 0.2,
      "validations": 0,
      "status": "pending_veto",
      "conditional": null,
      "category": "preference"
    },
    {
      "id": "hyp_1767071609_2",
      "created_ts": 1767071609.826809,
      "pattern": "helpful",
      "evidence": [],
      "weight": 0.2,
      "validations": 0,
      "status": "pending_veto",
      "conditional": null,
      "category": "preference"
    },
    {
      "id": "hyp_1767071609_3",
      "created_ts": 1767071609.826809,
      "pattern": "gentle",
      "evidence": [],
      "weight": 0.2,
      "validations": 0,
      "status": "pending_veto",
      "conditional": null,
      "category": "preference"
    },
    {
      "id": "hyp_1767071609_4",
      "created_ts": 1767071609.826809,
      "pattern": "steady",
      "evidence": [],
      "weight": 0.2,
      "validations": 0,
      "status": "pending_veto",
      "conditional": null,
      "category": "preference"
    },
    {
      "id": "hyp_1767071611_0",
      "created_ts": 1767071611.0342753,
      "pattern": "keep building",
      "evidence": [],
      "weight": 0.2,
      "validations": 0,
      "status": "pending_veto",
      "conditional": null,
      "category": "preference"
    },
    {
      "id": "hyp_1767071611_1",
      "created_ts": 1767071611.0342753,
      "pattern": "warm",
      "evidence": [],
      "weight": 0.2,
      "validations": 0,
      "status": "pending_veto",
      "conditional": null,
      "category": "preference"
    },
    {
      "id": "hyp_1767071611_2",
      "created_ts": 1767071611.0342753,
      "pattern": "helpful",
      "evidence": [],
      "weight": 0.2,
      "validations": 0,
      "status": "pending_veto",
      "conditional": null,
      "category": "preference"
    },
    {
      "id": "hyp_1767071611_3",
      "created_ts": 1767071611.0342753,
      "pattern": "gentle",
      "evidence": [],
      "weight": 0.2,
      "validations": 0,
      "status": "pending_veto",
      "conditional": null,
      "category": "preference"
    },
    {
      "id": "hyp_1767071611_4",
      "created_ts": 1767071611.0342753,
      "pattern": "steady",
      "evidence": [],
      "weight": 0.2,
      "validations": 0,
      "status": "pending_veto",
      "conditional": null,
      "category": "preference"
    },
    {
      "id": "hyp_1767071612_0",
      "created_ts": 1767071612.0952098,
      "pattern": "keep building",
      "evidence": [],
      "weight": 0.2,
      "validations": 0,
      "status": "pending_veto",
      "conditional": null,
      "category": "preference"
    },
    {
      "id": "hyp_1767071612_1",
      "created_ts": 1767071612.0952098,
      "pattern": "warm",
      "evidence": [],
      "weight": 0.2,
      "validations": 0,
      "status": "pending_veto",
      "conditional": null,
      "category": "preference"
    },
    {
      "id": "hyp_1767071612_2",
      "created_ts": 1767071612.0952098,
      "pattern": "helpful",
      "evidence": [],
      "weight": 0.2,
      "validations": 0,
      "status": "pending_veto",
      "conditional": null,
      "category": "preference"
    },
    {
      "id": "hyp_1767071612_3",
      "created_ts": 1767071612.0952098,
      "pattern": "gentle",
      "evidence": [],
      "weight": 0.2,
      "validations": 0,
      "status": "pending_veto",
      "conditional": null,
      "category": "preference"
    },
    {
      "id": "hyp_1767071612_4",
      "created_ts": 1767071612.0952098,
      "pattern": "steady",
      "evidence": [],
      "weight": 0.2,
      "validations": 0,
      "status": "pending_veto",
      "conditional": null,
      "category": "preference"
    },
    {
      "id": "hyp_1767071613_0",
      "created_ts": 1767071613.0676942,
      "pattern": "keep building",
      "evidence": [],
      "weight": 0.2,
      "validations": 0,
      "status": "pending_veto",
      "conditional": null,
      "category": "preference"
    },
    {
      "id": "hyp_1767071613_1",
      "created_ts": 1767071613.0676942,
      "pattern": "warm",
      "evidence": [],
      "weight": 0.2,
      "validations": 0,
      "status": "pending_veto",
      "conditional": null,
      "category": "preference"
    },
    {
      "id": "hyp_1767071613_2",
      "created_ts": 1767071613.0676942,
      "pattern": "helpful",
      "evidence": [],
      "weight": 0.2,
      "validations": 0,
      "status": "pending_veto",
      "conditional": null,
      "category": "preference"
    },
    {
      "id": "hyp_1767071613_3",
      "created_ts": 1767071613.0676942,
      "pattern": "gentle",
      "evidence": [],
      "weight": 0.2,
      "validations": 0,
      "status": "pending_veto",
      "conditional": null,
      "category": "preference"
    },
    {
      "id": "hyp_1767071613_4",
      "created_ts": 1767071613.0676942,
      "pattern": "steady",
      "evidence": [],
      "weight": 0.2,
      "validations": 0,
      "status": "pending_veto",
      "conditional": null,
      "category": "preference"
    },
    {
      "id": "hyp_1767071614_0",
      "created_ts": 1767071614.0502923,
      "pattern": "keep building",
      "evidence": [],
      "weight": 0.2,
      "validations": 0,
      "status": "pending_veto",
      "conditional": null,
      "category": "preference"
    },
    {
      "id": "hyp_1767071614_1",
      "created_ts": 1767071614.0502923,
      "pattern": "warm",
      "evidence": [],
      "weight": 0.2,
      "validations": 0,
      "status": "pending_veto",
      "conditional": null,
      "category": "preference"
    },
    {
      "id": "hyp_1767071614_2",
      "created_ts": 1767071614.0502923,
      "pattern": "helpful",
      "evidence": [],
      "weight": 0.2,
      "validations": 0,
      "status": "pending_veto",
      "conditional": null,
      "category": "preference"
    },
    {
      "id": "hyp_1767071614_3",
      "created_ts": 1767071614.0502923,
      "pattern": "gentle",
      "evidence": [],
      "weight": 0.2,
      "validations": 0,
      "status": "pending_veto",
      "conditional": null,
      "category": "preference"
    },
    {
      "id": "hyp_1767071614_4",
      "created_ts": 1767071614.0502923,
      "pattern": "steady",
      "evidence": [],
      "weight": 0.2,
      "validations": 0,
      "status": "pending_veto",
      "conditional": null,
      "category": "preference"
    },
    {
      "id": "hyp_1767071615_0",
      "created_ts": 1767071615.0176618,
      "pattern": "keep building",
      "evidence": [],
      "weight": 0.2,
      "validations": 0,
      "status": "pending_veto",
      "conditional": null,
      "category": "preference"
    },
    {
      "id": "hyp_1767071615_1",
      "created_ts": 1767071615.0176618,
      "pattern": "warm",
      "evidence": [],
      "weight": 0.2,
      "validations": 0,
      "status": "pending_veto",
      "conditional": null,
      "category": "preference"
    },
    {
      "id": "hyp_1767071615_2",
      "created_ts": 1767071615.0176618,
      "pattern": "helpful",
      "evidence": [],
      "weight": 0.2,
      "validations": 0,
      "status": "pending_veto",
      "conditional": null,
      "category": "preference"
    },
    {
      "id": "hyp_1767071615_3",
      "created_ts": 1767071615.0176618,
      "pattern": "gentle",
      "evidence": [],
      "weight": 0.2,
      "validations": 0,
      "status": "pending_veto",
      "conditional": null,
      "category": "preference"
    },
    {
      "id": "hyp_1767071615_4",
      "created_ts": 1767071615.0176618,
      "pattern": "steady",
      "evidence": [],
      "weight": 0.2,
      "validations": 0,
      "status": "pending_veto",
      "conditional": null,
      "category": "preference"
    },
    {
      "id": "hyp_1767071616_0",
      "created_ts": 1767071616.93025,
      "pattern": "keep building",
      "evidence": [],
      "weight": 0.2,
      "validations": 0,
      "status": "pending_veto",
      "conditional": null,
      "category": "preference"
    },
    {
      "id": "hyp_1767071616_1",
      "created_ts": 1767071616.93025,
      "pattern": "warm",
      "evidence": [],
      "weight": 0.2,
      "validations": 0,
      "status": "pending_veto",
      "conditional": null,
      "category": "preference"
    },
    {
      "id": "hyp_1767071616_2",
      "created_ts": 1767071616.93025,
      "pattern": "helpful",
      "evidence": [],
      "weight": 0.2,
      "validations": 0,
      "status": "pending_veto",
      "conditional": null,
      "category": "preference"
    },
    {
      "id": "hyp_1767071616_3",
      "created_ts": 1767071616.93025,
      "pattern": "gentle",
      "evidence": [],
      "weight": 0.2,
      "validations": 0,
      "status": "pending_veto",
      "conditional": null,
      "category": "preference"
    },
    {
      "id": "hyp_1767071616_4",
      "created_ts": 1767071616.93025,
      "pattern": "steady",
      "evidence": [],
      "weight": 0.2,
      "validations": 0,
      "status": "pending_veto",
      "conditional": null,
      "category": "preference"
    },
    {
      "id": "hyp_1767071617_0",
      "created_ts": 1767071617.918126,
      "pattern": "keep building",
      "evidence": [],
      "weight": 0.2,
      "validations": 0,
      "status": "pending_veto",
      "conditional": null,
      "category": "preference"
    },
    {
      "id": "hyp_1767071617_1",
      "created_ts": 1767071617.918126,
      "pattern": "warm",
      "evidence": [],
      "weight": 0.2,
      "validations": 0,
      "status": "pending_veto",
      "conditional": null,
      "category": "preference"
    },
    {
      "id": "hyp_1767071617_2",
      "created_ts": 1767071617.918126,
      "pattern": "helpful",
      "evidence": [],
      "weight": 0.2,
      "validations": 0,
      "status": "pending_veto",
      "conditional": null,
      "category": "preference"
    },
    {
      "id": "hyp_1767071617_3",
      "created_ts": 1767071617.918126,
      "pattern": "gentle",
      "evidence": [],
      "weight": 0.2,
      "validations": 0,
      "status": "pending_veto",
      "conditional": null,
      "category": "preference"
    },
    {
      "id": "hyp_1767071617_4",
      "created_ts": 1767071617.918126,
      "pattern": "steady",
      "evidence": [],
      "weight": 0.2,
      "validations": 0,
      "status": "pending_veto",
      "conditional": null,
      "category": "preference"
    },
    {
      "id": "hyp_1767072160_0",
      "created_ts": 1767072160.6799753,
      "pattern": "keep building",
      "evidence": [],
      "weight": 0.2,
      "validations": 0,
      "status": "pending_veto",
      "conditional": null,
      "category": "preference"
    },
    {
      "id": "hyp_1767072160_1",
      "created_ts": 1767072160.6799753,
      "pattern": "warm",
      "evidence": [],
      "weight": 0.2,
      "validations": 0,
      "status": "pending_veto",
      "conditional": null,
      "category": "preference"
    },
    {
      "id": "hyp_1767072160_2",
      "created_ts": 1767072160.6799753,
      "pattern": "helpful",
      "evidence": [],
      "weight": 0.2,
      "validations": 0,
      "status": "pending_veto",
      "conditional": null,
      "category": "preference"
    },
    {
      "id": "hyp_1767072160_3",
      "created_ts": 1767072160.6799753,
      "pattern": "gentle",
      "evidence": [],
      "weight": 0.2,
      "validations": 0,
      "status": "pending_veto",
      "conditional": null,
      "category": "preference"
    },
    {
      "id": "hyp_1767072160_4",
      "created_ts": 1767072160.6799753,
      "pattern": "steady",
      "evidence": [],
      "weight": 0.2,
      "validations": 0,
      "status": "pending_veto",
      "conditional": null,
      "category": "preference"
    },
    {
      "id": "hyp_1767072164_0",
      "created_ts": 1767072164.8036523,
      "pattern": "keep building",
      "evidence": [],
      "weight": 0.2,
      "validations": 0,
      "status": "pending_veto",
      "conditional": null,
      "category": "preference"
    },
    {
      "id": "hyp_1767072164_1",
      "created_ts": 1767072164.8036523,
      "pattern": "warm",
      "evidence": [],
      "weight": 0.2,
      "validations": 0,
      "status": "pending_veto",
      "conditional": null,
      "category": "preference"
    },
    {
      "id": "hyp_1767072164_2",
      "created_ts": 1767072164.8036523,
      "pattern": "helpful",
      "evidence": [],
      "weight": 0.2,
      "validations": 0,
      "status": "pending_veto",
      "conditional": null,
      "category": "preference"
    },
    {
      "id": "hyp_1767072164_3",
      "created_ts": 1767072164.8036523,
      "pattern": "gentle",
      "evidence": [],
      "weight": 0.2,
      "validations": 0,
      "status": "pending_veto",
      "conditional": null,
      "category": "preference"
    },
    {
      "id": "hyp_1767072164_4",
      "created_ts": 1767072164.8036523,
      "pattern": "steady",
      "evidence": [],
      "weight": 0.2,
      "validations": 0,
      "status": "pending_veto",
      "conditional": null,
      "category": "preference"
    },
    {
      "id": "hyp_1767072165_0",
      "created_ts": 1767072165.760703,
      "pattern": "keep building",
      "evidence": [],
      "weight": 0.2,
      "validations": 0,
      "status": "pending_veto",
      "conditional": null,
      "category": "preference"
    },
    {
      "id": "hyp_1767072165_1",
      "created_ts": 1767072165.760703,
      "pattern": "warm",
      "evidence": [],
      "weight": 0.2,
      "validations": 0,
      "status": "pending_veto",
      "conditional": null,
      "category": "preference"
    },
    {
      "id": "hyp_1767072165_2",
      "created_ts": 1767072165.760703,
      "pattern": "helpful",
      "evidence": [],
      "weight": 0.2,
      "validations": 0,
      "status": "pending_veto",
      "conditional": null,
      "category": "preference"
    },
    {
      "id": "hyp_1767072165_3",
      "created_ts": 1767072165.760703,
      "pattern": "gentle",
      "evidence": [],
      "weight": 0.2,
      "validations": 0,
      "status": "pending_veto",
      "conditional": null,
      "category": "preference"
    },
    {
      "id": "hyp_1767072165_4",
      "created_ts": 1767072165.760703,
      "pattern": "steady",
      "evidence": [],
      "weight": 0.2,
      "validations": 0,
      "status": "pending_veto",
      "conditional": null,
      "category": "preference"
    },
    {
      "id": "hyp_1767072166_0",
      "created_ts": 1767072166.8896153,
      "pattern": "keep building",
      "evidence": [],
      "weight": 0.2,
      "validations": 0,
      "status": "pending_veto",
      "conditional": null,
      "category": "preference"
    },
    {
      "id": "hyp_1767072166_1",
      "created_ts": 1767072166.8896153,
      "pattern": "warm",
      "evidence": [],
      "weight": 0.2,
      "validations": 0,
      "status": "pending_veto",
      "conditional": null,
      "category": "preference"
    },
    {
      "id": "hyp_1767072166_2",
      "created_ts": 1767072166.8896153,
      "pattern": "helpful",
      "evidence": [],
      "weight": 0.2,
      "validations": 0,
      "status": "pending_veto",
      "conditional": null,
      "category": "preference"
    },
    {
      "id": "hyp_1767072166_3",
      "created_ts": 1767072166.8896153,
      "pattern": "gentle",
      "evidence": [],
      "weight": 0.2,
      "validations": 0,
      "status": "pending_veto",
      "conditional": null,
      "category": "preference"
    },
    {
      "id": "hyp_1767072166_4",
      "created_ts": 1767072166.8896153,
      "pattern": "steady",
      "evidence": [],
      "weight": 0.2,
      "validations": 0,
      "status": "pending_veto",
      "conditional": null,
      "category": "preference"
    },
    {
      "id": "hyp_1767072167_0",
      "created_ts": 1767072167.8410666,
      "pattern": "keep building",
      "evidence": [],
      "weight": 0.2,
      "validations": 0,
      "status": "pending_veto",
      "conditional": null,
      "category": "preference"
    },
    {
      "id": "hyp_1767072167_1",
      "created_ts": 1767072167.8410666,
      "pattern": "warm",
      "evidence": [],
      "weight": 0.2,
      "validations": 0,
      "status": "pending_veto",
      "conditional": null,
      "category": "preference"
    },
    {
      "id": "hyp_1767072167_2",
      "created_ts": 1767072167.8410666,
      "pattern": "helpful",
      "evidence": [],
      "weight": 0.2,
      "validations": 0,
      "status": "pending_veto",
      "conditional": null,
      "category": "preference"
    },
    {
      "id": "hyp_1767072167_3",
      "created_ts": 1767072167.8410666,
      "pattern": "gentle",
      "evidence": [],
      "weight": 0.2,
      "validations": 0,
      "status": "pending_veto",
      "conditional": null,
      "category": "preference"
    },
    {
      "id": "hyp_1767072167_4",
      "created_ts": 1767072167.8410666,
      "pattern": "steady",
      "evidence": [],
      "weight": 0.2,
      "validations": 0,
      "status": "pending_veto",
      "conditional": null,
      "category": "preference"
    },
    {
      "id": "hyp_1767072168_0",
      "created_ts": 1767072168.7571192,
      "pattern": "keep building",
      "evidence": [],
      "weight": 0.2,
      "validations": 0,
      "status": "pending_veto",
      "conditional": null,
      "category": "preference"
    },
    {
      "id": "hyp_1767072168_1",
      "created_ts": 1767072168.7571192,
      "pattern": "warm",
      "evidence": [],
      "weight": 0.2,
      "validations": 0,
      "status": "pending_veto",
      "conditional": null,
      "category": "preference"
    },
    {
      "id": "hyp_1767072168_2",
      "created_ts": 1767072168.7571192,
      "pattern": "helpful",
      "evidence": [],
      "weight": 0.2,
      "validations": 0,
      "status": "pending_veto",
      "conditional": null,
      "category": "preference"
    },
    {
      "id": "hyp_1767072168_3",
      "created_ts": 1767072168.7571192,
      "pattern": "gentle",
      "evidence": [],
      "weight": 0.2,
      "validations": 0,
      "status": "pending_veto",
      "conditional": null,
      "category": "preference"
    },
    {
      "id": "hyp_1767072168_4",
      "created_ts": 1767072168.7571192,
      "pattern": "steady",
      "evidence": [],
      "weight": 0.2,
      "validations": 0,
      "status": "pending_veto",
      "conditional": null,
      "category": "preference"
    },
    {
      "id": "hyp_1767072169_0",
      "created_ts": 1767072169.6870306,
      "pattern": "keep building",
      "evidence": [],
      "weight": 0.2,
      "validations": 0,
      "status": "pending_veto",
      "conditional": null,
      "category": "preference"
    },
    {
      "id": "hyp_1767072169_1",
      "created_ts": 1767072169.6870306,
      "pattern": "warm",
      "evidence": [],
      "weight": 0.2,
      "validations": 0,
      "status": "pending_veto",
      "conditional": null,
      "category": "preference"
    },
    {
      "id": "hyp_1767072169_2",
      "created_ts": 1767072169.6870306,
      "pattern": "helpful",
      "evidence": [],
      "weight": 0.2,
      "validations": 0,
      "status": "pending_veto",
      "conditional": null,
      "category": "preference"
    },
    {
      "id": "hyp_1767072169_3",
      "created_ts": 1767072169.6870306,
      "pattern": "gentle",
      "evidence": [],
      "weight": 0.2,
      "validations": 0,
      "status": "pending_veto",
      "conditional": null,
      "category": "preference"
    },
    {
      "id": "hyp_1767072169_4",
      "created_ts": 1767072169.6870306,
      "pattern": "steady",
      "evidence": [],
      "weight": 0.2,
      "validations": 0,
      "status": "pending_veto",
      "conditional": null,
      "category": "preference"
    },
    {
      "id": "hyp_1767072170_0",
      "created_ts": 1767072170.5694706,
      "pattern": "keep building",
      "evidence": [],
      "weight": 0.2,
      "validations": 0,
      "status": "pending_veto",
      "conditional": null,
      "category": "preference"
    },
    {
      "id": "hyp_1767072170_1",
      "created_ts": 1767072170.5694706,
      "pattern": "warm",
      "evidence": [],
      "weight": 0.2,
      "validations": 0,
      "status": "pending_veto",
      "conditional": null,
      "category": "preference"
    },
    {
      "id": "hyp_1767072170_2",
      "created_ts": 1767072170.5694706,
      "pattern": "helpful",
      "evidence": [],
      "weight": 0.2,
      "validations": 0,
      "status": "pending_veto",
      "conditional": null,
      "category": "preference"
    },
    {
      "id": "hyp_1767072170_3",
      "created_ts": 1767072170.5694706,
      "pattern": "gentle",
      "evidence": [],
      "weight": 0.2,
      "validations": 0,
      "status": "pending_veto",
      "conditional": null,
      "category": "preference"
    },
    {
      "id": "hyp_1767072170_4",
      "created_ts": 1767072170.5694706,
      "pattern": "steady",
      "evidence": [],
      "weight": 0.2,
      "validations": 0,
      "status": "pending_veto",
      "conditional": null,
      "category": "preference"
    },
    {
      "id": "hyp_1767072171_0",
      "created_ts": 1767072171.4358196,
      "pattern": "keep building",
      "evidence": [],
      "weight": 0.2,
      "validations": 0,
      "status": "pending_veto",
      "conditional": null,
      "category": "preference"
    },
    {
      "id": "hyp_1767072171_1",
      "created_ts": 1767072171.4358196,
      "pattern": "warm",
      "evidence": [],
      "weight": 0.2,
      "validations": 0,
      "status": "pending_veto",
      "conditional": null,
      "category": "preference"
    },
    {
      "id": "hyp_1767072171_2",
      "created_ts": 1767072171.4358196,
      "pattern": "helpful",
      "evidence": [],
      "weight": 0.2,
      "validations": 0,
      "status": "pending_veto",
      "conditional": null,
      "category": "preference"
    },
    {
      "id": "hyp_1767072171_3",
      "created_ts": 1767072171.4358196,
      "pattern": "gentle",
      "evidence": [],
      "weight": 0.2,
      "validations": 0,
      "status": "pending_veto",
      "conditional": null,
      "category": "preference"
    },
    {
      "id": "hyp_1767072171_4",
      "created_ts": 1767072171.4358196,
      "pattern": "steady",
      "evidence": [],
      "weight": 0.2,
      "validations": 0,
      "status": "pending_veto",
      "conditional": null,
      "category": "preference"
    },
    {
      "id": "hyp_1767072172_0",
      "created_ts": 1767072172.3684587,
      "pattern": "keep building",
      "evidence": [],
      "weight": 0.2,
      "validations": 0,
      "status": "pending_veto",
      "conditional": null,
      "category": "preference"
    },
    {
      "id": "hyp_1767072172_1",
      "created_ts": 1767072172.3684587,
      "pattern": "warm",
      "evidence": [],
      "weight": 0.2,
      "validations": 0,
      "status": "pending_veto",
      "conditional": null,
      "category": "preference"
    },
    {
      "id": "hyp_1767072172_2",
      "created_ts": 1767072172.3684587,
      "pattern": "helpful",
      "evidence": [],
      "weight": 0.2,
      "validations": 0,
      "status": "pending_veto",
      "conditional": null,
      "category": "preference"
    },
    {
      "id": "hyp_1767072172_3",
      "created_ts": 1767072172.3684587,
      "pattern": "gentle",
      "evidence": [],
      "weight": 0.2,
      "validations": 0,
      "status": "pending_veto",
      "conditional": null,
      "category": "preference"
    },
    {
      "id": "hyp_1767072172_4",
      "created_ts": 1767072172.3684587,
      "pattern": "steady",
      "evidence": [],
      "weight": 0.2,
      "validations": 0,
      "status": "pending_veto",
      "conditional": null,
      "category": "preference"
    },
    {
      "id": "hyp_1767072173_0",
      "created_ts": 1767072173.2305112,
      "pattern": "keep building",
      "evidence": [],
      "weight": 0.2,
      "validations": 0,
      "status": "pending_veto",
      "conditional": null,
      "category": "preference"
    },
    {
      "id": "hyp_1767072173_1",
      "created_ts": 1767072173.2305112,
      "pattern": "warm",
      "evidence": [],
      "weight": 0.2,
      "validations": 0,
      "status": "pending_veto",
      "conditional": null,
      "category": "preference"
    },
    {
      "id": "hyp_1767072173_2",
      "created_ts": 1767072173.2305112,
      "pattern": "helpful",
      "evidence": [],
      "weight": 0.2,
      "validations": 0,
      "status": "pending_veto",
      "conditional": null,
      "category": "preference"
    },
    {
      "id": "hyp_1767072173_3",
      "created_ts": 1767072173.2305112,
      "pattern": "gentle",
      "evidence": [],
      "weight": 0.2,
      "validations": 0,
      "status": "pending_veto",
      "conditional": null,
      "category": "preference"
    },
    {
      "id": "hyp_1767072173_4",
      "created_ts": 1767072173.2305112,
      "pattern": "steady",
      "evidence": [],
      "weight": 0.2,
      "validations": 0,
      "status": "pending_veto",
      "conditional": null,
      "category": "preference"
    },
    {
      "id": "hyp_1767072174_0",
      "created_ts": 1767072174.1160886,
      "pattern": "keep building",
      "evidence": [],
      "weight": 0.2,
      "validations": 0,
      "status": "pending_veto",
      "conditional": null,
      "category": "preference"
    },
    {
      "id": "hyp_1767072174_1",
      "created_ts": 1767072174.1160886,
      "pattern": "warm",
      "evidence": [],
      "weight": 0.2,
      "validations": 0,
      "status": "pending_veto",
      "conditional": null,
      "category": "preference"
    },
    {
      "id": "hyp_1767072174_2",
      "created_ts": 1767072174.1160886,
      "pattern": "helpful",
      "evidence": [],
      "weight": 0.2,
      "validations": 0,
      "status": "pending_veto",
      "conditional": null,
      "category": "preference"
    },
    {
      "id": "hyp_1767072174_3",
      "created_ts": 1767072174.1160886,
      "pattern": "gentle",
      "evidence": [],
      "weight": 0.2,
      "validations": 0,
      "status": "pending_veto",
      "conditional": null,
      "category": "preference"
    },
    {
      "id": "hyp_1767072174_4",
      "created_ts": 1767072174.1160886,
      "pattern": "steady",
      "evidence": [],
      "weight": 0.2,
      "validations": 0,
      "status": "pending_veto",
      "conditional": null,
      "category": "preference"
    },
    {
      "id": "hyp_1767072197_0",
      "created_ts": 1767072197.7641249,
      "pattern": "keep building",
      "evidence": [],
      "weight": 0.2,
      "validations": 0,
      "status": "pending_veto",
      "conditional": null,
      "category": "preference"
    },
    {
      "id": "hyp_1767072197_1",
      "created_ts": 1767072197.7641249,
      "pattern": "warm",
      "evidence": [],
      "weight": 0.2,
      "validations": 0,
      "status": "pending_veto",
      "conditional": null,
      "category": "preference"
    },
    {
      "id": "hyp_1767072197_2",
      "created_ts": 1767072197.7641249,
      "pattern": "helpful",
      "evidence": [],
      "weight": 0.2,
      "validations": 0,
      "status": "pending_veto",
      "conditional": null,
      "category": "preference"
    },
    {
      "id": "hyp_1767072197_3",
      "created_ts": 1767072197.7641249,
      "pattern": "gentle",
      "evidence": [],
      "weight": 0.2,
      "validations": 0,
      "status": "pending_veto",
      "conditional": null,
      "category": "preference"
    },
    {
      "id": "hyp_1767072197_4",
      "created_ts": 1767072197.7641249,
      "pattern": "steady",
      "evidence": [],
      "weight": 0.2,
      "validations": 0,
      "status": "pending_veto",
      "conditional": null,
      "category": "preference"
    },
    {
      "id": "hyp_1767072656_0",
      "created_ts": 1767072656.6602826,
      "pattern": "keep building",
      "evidence": [],
      "weight": 0.2,
      "validations": 0,
      "status": "pending_veto",
      "conditional": null,
      "category": "preference"
    },
    {
      "id": "hyp_1767072656_1",
      "created_ts": 1767072656.6602826,
      "pattern": "warm",
      "evidence": [],
      "weight": 0.2,
      "validations": 0,
      "status": "pending_veto",
      "conditional": null,
      "category": "preference"
    },
    {
      "id": "hyp_1767072656_2",
      "created_ts": 1767072656.6602826,
      "pattern": "helpful",
      "evidence": [],
      "weight": 0.2,
      "validations": 0,
      "status": "pending_veto",
      "conditional": null,
      "category": "preference"
    },
    {
      "id": "hyp_1767072656_3",
      "created_ts": 1767072656.6602826,
      "pattern": "gentle",
      "evidence": [],
      "weight": 0.2,
      "validations": 0,
      "status": "pending_veto",
      "conditional": null,
      "category": "preference"
    },
    {
      "id": "hyp_1767072656_4",
      "created_ts": 1767072656.6602826,
      "pattern": "steady",
      "evidence": [],
      "weight": 0.2,
      "validations": 0,
      "status": "pending_veto",
      "conditional": null,
      "category": "preference"
    },
    {
      "id": "hyp_1767072660_0",
      "created_ts": 1767072660.0852928,
      "pattern": "keep building",
      "evidence": [],
      "weight": 0.2,
      "validations": 0,
      "status": "pending_veto",
      "conditional": null,
      "category": "preference"
    },
    {
      "id": "hyp_1767072660_1",
      "created_ts": 1767072660.0852928,
      "pattern": "warm",
      "evidence": [],
      "weight": 0.2,
      "validations": 0,
      "status": "pending_veto",
      "conditional": null,
      "category": "preference"
    },
    {
      "id": "hyp_1767072660_2",
      "created_ts": 1767072660.0852928,
      "pattern": "helpful",
      "evidence": [],
      "weight": 0.2,
      "validations": 0,
      "status": "pending_veto",
      "conditional": null,
      "category": "preference"
    },
    {
      "id": "hyp_1767072660_3",
      "created_ts": 1767072660.0852928,
      "pattern": "gentle",
      "evidence": [],
      "weight": 0.2,
      "validations": 0,
      "status": "pending_veto",
      "conditional": null,
      "category": "preference"
    },
    {
      "id": "hyp_1767072660_4",
      "created_ts": 1767072660.0852928,
      "pattern": "steady",
      "evidence": [],
      "weight": 0.2,
      "validations": 0,
      "status": "pending_veto",
      "conditional": null,
      "category": "preference"
    },
    {
      "id": "hyp_1767072661_0",
      "created_ts": 1767072661.6767392,
      "pattern": "keep building",
      "evidence": [],
      "weight": 0.2,
      "validations": 0,
      "status": "pending_veto",
      "conditional": null,
      "category": "preference"
    },
    {
      "id": "hyp_1767072661_1",
      "created_ts": 1767072661.6767392,
      "pattern": "warm",
      "evidence": [],
      "weight": 0.2,
      "validations": 0,
      "status": "pending_veto",
      "conditional": null,
      "category": "preference"
    },
    {
      "id": "hyp_1767072661_2",
      "created_ts": 1767072661.6767392,
      "pattern": "helpful",
      "evidence": [],
      "weight": 0.2,
      "validations": 0,
      "status": "pending_veto",
      "conditional": null,
      "category": "preference"
    },
    {
      "id": "hyp_1767072661_3",
      "created_ts": 1767072661.6767392,
      "pattern": "gentle",
      "evidence": [],
      "weight": 0.2,
      "validations": 0,
      "status": "pending_veto",
      "conditional": null,
      "category": "preference"
    },
    {
      "id": "hyp_1767072661_4",
      "created_ts": 1767072661.6767392,
      "pattern": "steady",
      "evidence": [],
      "weight": 0.2,
      "validations": 0,
      "status": "pending_veto",
      "conditional": null,
      "category": "preference"
    },
    {
      "id": "hyp_1767072663_0",
      "created_ts": 1767072663.2524664,
      "pattern": "keep building",
      "evidence": [],
      "weight": 0.2,
      "validations": 0,
      "status": "pending_veto",
      "conditional": null,
      "category": "preference"
    },
    {
      "id": "hyp_1767072663_1",
      "created_ts": 1767072663.2524664,
      "pattern": "warm",
      "evidence": [],
      "weight": 0.2,
      "validations": 0,
      "status": "pending_veto",
      "conditional": null,
      "category": "preference"
    },
    {
      "id": "hyp_1767072663_2",
      "created_ts": 1767072663.2524664,
      "pattern": "helpful",
      "evidence": [],
      "weight": 0.2,
      "validations": 0,
      "status": "pending_veto",
      "conditional": null,
      "category": "preference"
    },
    {
      "id": "hyp_1767072663_3",
      "created_ts": 1767072663.2524664,
      "pattern": "gentle",
      "evidence": [],
      "weight": 0.2,
      "validations": 0,
      "status": "pending_veto",
      "conditional": null,
      "category": "preference"
    },
    {
      "id": "hyp_1767072663_4",
      "created_ts": 1767072663.2524664,
      "pattern": "steady",
      "evidence": [],
      "weight": 0.2,
      "validations": 0,
      "status": "pending_veto",
      "conditional": null,
      "category": "preference"
    },
    {
      "id": "hyp_1767072664_0",
      "created_ts": 1767072664.8489192,
      "pattern": "keep building",
      "evidence": [],
      "weight": 0.2,
      "validations": 0,
      "status": "pending_veto",
      "conditional": null,
      "category": "preference"
    },
    {
      "id": "hyp_1767072664_1",
      "created_ts": 1767072664.8489192,
      "pattern": "warm",
      "evidence": [],
      "weight": 0.2,
      "validations": 0,
      "status": "pending_veto",
      "conditional": null,
      "category": "preference"
    },
    {
      "id": "hyp_1767072664_2",
      "created_ts": 1767072664.8489192,
      "pattern": "helpful",
      "evidence": [],
      "weight": 0.2,
      "validations": 0,
      "status": "pending_veto",
      "conditional": null,
      "category": "preference"
    },
    {
      "id": "hyp_1767072664_3",
      "created_ts": 1767072664.8489192,
      "pattern": "gentle",
      "evidence": [],
      "weight": 0.2,
      "validations": 0,
      "status": "pending_veto",
      "conditional": null,
      "category": "preference"
    },
    {
      "id": "hyp_1767072664_4",
      "created_ts": 1767072664.8489192,
      "pattern": "steady",
      "evidence": [],
      "weight": 0.2,
      "validations": 0,
      "status": "pending_veto",
      "conditional": null,
      "category": "preference"
    },
    {
      "id": "hyp_1767072666_0",
      "created_ts": 1767072666.3975852,
      "pattern": "keep building",
      "evidence": [],
      "weight": 0.2,
      "validations": 0,
      "status": "pending_veto",
      "conditional": null,
      "category": "preference"
    },
    {
      "id": "hyp_1767072666_1",
      "created_ts": 1767072666.3975852,
      "pattern": "warm",
      "evidence": [],
      "weight": 0.2,
      "validations": 0,
      "status": "pending_veto",
      "conditional": null,
      "category": "preference"
    },
    {
      "id": "hyp_1767072666_2",
      "created_ts": 1767072666.3975852,
      "pattern": "helpful",
      "evidence": [],
      "weight": 0.2,
      "validations": 0,
      "status": "pending_veto",
      "conditional": null,
      "category": "preference"
    },
    {
      "id": "hyp_1767072666_3",
      "created_ts": 1767072666.3975852,
      "pattern": "gentle",
      "evidence": [],
      "weight": 0.2,
      "validations": 0,
      "status": "pending_veto",
      "conditional": null,
      "category": "preference"
    },
    {
      "id": "hyp_1767072666_4",
      "created_ts": 1767072666.3975852,
      "pattern": "steady",
      "evidence": [],
      "weight": 0.2,
      "validations": 0,
      "status": "pending_veto",
      "conditional": null,
      "category": "preference"
    },
    {
      "id": "hyp_1767072668_0",
      "created_ts": 1767072668.0696297,
      "pattern": "keep building",
      "evidence": [],
      "weight": 0.2,
      "validations": 0,
      "status": "pending_veto",
      "conditional": null,
      "category": "preference"
    },
    {
      "id": "hyp_1767072668_1",
      "created_ts": 1767072668.0696297,
      "pattern": "warm",
      "evidence": [],
      "weight": 0.2,
      "validations": 0,
      "status": "pending_veto",
      "conditional": null,
      "category": "preference"
    },
    {
      "id": "hyp_1767072668_2",
      "created_ts": 1767072668.0696297,
      "pattern": "helpful",
      "evidence": [],
      "weight": 0.2,
      "validations": 0,
      "status": "pending_veto",
      "conditional": null,
      "category": "preference"
    },
    {
      "id": "hyp_1767072668_3",
      "created_ts": 1767072668.0696297,
      "pattern": "gentle",
      "evidence": [],
      "weight": 0.2,
      "validations": 0,
      "status": "pending_veto",
      "conditional": null,
      "category": "preference"
    },
    {
      "id": "hyp_1767072668_4",
      "created_ts": 1767072668.0696297,
      "pattern": "steady",
      "evidence": [],
      "weight": 0.2,
      "validations": 0,
      "status": "pending_veto",
      "conditional": null,
      "category": "preference"
    },
    {
      "id": "hyp_1767072669_0",
      "created_ts": 1767072669.8063238,
      "pattern": "keep building",
      "evidence": [],
      "weight": 0.2,
      "validations": 0,
      "status": "pending_veto",
      "conditional": null,
      "category": "preference"
    },
    {
      "id": "hyp_1767072669_1",
      "created_ts": 1767072669.8063238,
      "pattern": "warm",
      "evidence": [],
      "weight": 0.2,
      "validations": 0,
      "status": "pending_veto",
      "conditional": null,
      "category": "preference"
    },
    {
      "id": "hyp_1767072669_2",
      "created_ts": 1767072669.8063238,
      "pattern": "helpful",
      "evidence": [],
      "weight": 0.2,
      "validations": 0,
      "status": "pending_veto",
      "conditional": null,
      "category": "preference"
    },
    {
      "id": "hyp_1767072669_3",
      "created_ts": 1767072669.8063238,
      "pattern": "gentle",
      "evidence": [],
      "weight": 0.2,
      "validations": 0,
      "status": "pending_veto",
      "conditional": null,
      "category": "preference"
    },
    {
      "id": "hyp_1767072669_4",
      "created_ts": 1767072669.8063238,
      "pattern": "steady",
      "evidence": [],
      "weight": 0.2,
      "validations": 0,
      "status": "pending_veto",
      "conditional": null,
      "category": "preference"
    },
    {
      "id": "hyp_1767072671_0",
      "created_ts": 1767072671.9167972,
      "pattern": "keep building",
      "evidence": [],
      "weight": 0.2,
      "validations": 0,
      "status": "pending_veto",
      "conditional": null,
      "category": "preference"
    },
    {
      "id": "hyp_1767072671_1",
      "created_ts": 1767072671.9167972,
      "pattern": "warm",
      "evidence": [],
      "weight": 0.2,
      "validations": 0,
      "status": "pending_veto",
      "conditional": null,
      "category": "preference"
    },
    {
      "id": "hyp_1767072671_2",
      "created_ts": 1767072671.9167972,
      "pattern": "helpful",
      "evidence": [],
      "weight": 0.2,
      "validations": 0,
      "status": "pending_veto",
      "conditional": null,
      "category": "preference"
    },
    {
      "id": "hyp_1767072671_3",
      "created_ts": 1767072671.9167972,
      "pattern": "gentle",
      "evidence": [],
      "weight": 0.2,
      "validations": 0,
      "status": "pending_veto",
      "conditional": null,
      "category": "preference"
    },
    {
      "id": "hyp_1767072671_4",
      "created_ts": 1767072671.9167972,
      "pattern": "steady",
      "evidence": [],
      "weight": 0.2,
      "validations": 0,
      "status": "pending_veto",
      "conditional": null,
      "category": "preference"
    },
    {
      "id": "hyp_1767072673_0",
      "created_ts": 1767072673.6630278,
      "pattern": "keep building",
      "evidence": [],
      "weight": 0.2,
      "validations": 0,
      "status": "pending_veto",
      "conditional": null,
      "category": "preference"
    },
    {
      "id": "hyp_1767072673_1",
      "created_ts": 1767072673.6630278,
      "pattern": "warm",
      "evidence": [],
      "weight": 0.2,
      "validations": 0,
      "status": "pending_veto",
      "conditional": null,
      "category": "preference"
    },
    {
      "id": "hyp_1767072673_2",
      "created_ts": 1767072673.6630278,
      "pattern": "helpful",
      "evidence": [],
      "weight": 0.2,
      "validations": 0,
      "status": "pending_veto",
      "conditional": null,
      "category": "preference"
    },
    {
      "id": "hyp_1767072673_3",
      "created_ts": 1767072673.6630278,
      "pattern": "gentle",
      "evidence": [],
      "weight": 0.2,
      "validations": 0,
      "status": "pending_veto",
      "conditional": null,
      "category": "preference"
    },
    {
      "id": "hyp_1767072673_4",
      "created_ts": 1767072673.6630278,
      "pattern": "steady",
      "evidence": [],
      "weight": 0.2,
      "validations": 0,
      "status": "pending_veto",
      "conditional": null,
      "category": "preference"
    },
    {
      "id": "hyp_1767072675_0",
      "created_ts": 1767072675.5091965,
      "pattern": "keep building",
      "evidence": [],
      "weight": 0.2,
      "validations": 0,
      "status": "pending_veto",
      "conditional": null,
      "category": "preference"
    },
    {
      "id": "hyp_1767072675_1",
      "created_ts": 1767072675.5091965,
      "pattern": "warm",
      "evidence": [],
      "weight": 0.2,
      "validations": 0,
      "status": "pending_veto",
      "conditional": null,
      "category": "preference"
    },
    {
      "id": "hyp_1767072675_2",
      "created_ts": 1767072675.5091965,
      "pattern": "helpful",
      "evidence": [],
      "weight": 0.2,
      "validations": 0,
      "status": "pending_veto",
      "conditional": null,
      "category": "preference"
    },
    {
      "id": "hyp_1767072675_3",
      "created_ts": 1767072675.5091965,
      "pattern": "gentle",
      "evidence": [],
      "weight": 0.2,
      "validations": 0,
      "status": "pending_veto",
      "conditional": null,
      "category": "preference"
    },
    {
      "id": "hyp_1767072675_4",
      "created_ts": 1767072675.5091965,
      "pattern": "steady",
      "evidence": [],
      "weight": 0.2,
      "validations": 0,
      "status": "pending_veto",
      "conditional": null,
      "category": "preference"
    },
    {
      "id": "hyp_1767072677_0",
      "created_ts": 1767072677.2254782,
      "pattern": "keep building",
      "evidence": [],
      "weight": 0.2,
      "validations": 0,
      "status": "pending_veto",
      "conditional": null,
      "category": "preference"
    },
    {
      "id": "hyp_1767072677_1",
      "created_ts": 1767072677.2254782,
      "pattern": "warm",
      "evidence": [],
      "weight": 0.2,
      "validations": 0,
      "status": "pending_veto",
      "conditional": null,
      "category": "preference"
    },
    {
      "id": "hyp_1767072677_2",
      "created_ts": 1767072677.2254782,
      "pattern": "helpful",
      "evidence": [],
      "weight": 0.2,
      "validations": 0,
      "status": "pending_veto",
      "conditional": null,
      "category": "preference"
    },
    {
      "id": "hyp_1767072677_3",
      "created_ts": 1767072677.2254782,
      "pattern": "gentle",
      "evidence": [],
      "weight": 0.2,
      "validations": 0,
      "status": "pending_veto",
      "conditional": null,
      "category": "preference"
    },
    {
      "id": "hyp_1767072677_4",
      "created_ts": 1767072677.2254782,
      "pattern": "steady",
      "evidence": [],
      "weight": 0.2,
      "validations": 0,
      "status": "pending_veto",
      "conditional": null,
      "category": "preference"
    },
    {
      "id": "hyp_1767072732_0",
      "created_ts": 1767072732.2350116,
      "pattern": "keep building",
      "evidence": [],
      "weight": 0.2,
      "validations": 0,
      "status": "pending_veto",
      "conditional": null,
      "category": "preference"
    },
    {
      "id": "hyp_1767072732_1",
      "created_ts": 1767072732.2350116,
      "pattern": "warm",
      "evidence": [],
      "weight": 0.2,
      "validations": 0,
      "status": "pending_veto",
      "conditional": null,
      "category": "preference"
    },
    {
      "id": "hyp_1767072732_2",
      "created_ts": 1767072732.2350116,
      "pattern": "helpful",
      "evidence": [],
      "weight": 0.2,
      "validations": 0,
      "status": "pending_veto",
      "conditional": null,
      "category": "preference"
    },
    {
      "id": "hyp_1767072732_3",
      "created_ts": 1767072732.2350116,
      "pattern": "gentle",
      "evidence": [],
      "weight": 0.2,
      "validations": 0,
      "status": "pending_veto",
      "conditional": null,
      "category": "preference"
    },
    {
      "id": "hyp_1767072732_4",
      "created_ts": 1767072732.2350116,
      "pattern": "steady",
      "evidence": [],
      "weight": 0.2,
      "validations": 0,
      "status": "pending_veto",
      "conditional": null,
      "category": "preference"
    },
    {
      "id": "hyp_1767072735_0",
      "created_ts": 1767072735.8780673,
      "pattern": "keep building",
      "evidence": [],
      "weight": 0.2,
      "validations": 0,
      "status": "pending_veto",
      "conditional": null,
      "category": "preference"
    },
    {
      "id": "hyp_1767072735_1",
      "created_ts": 1767072735.8780673,
      "pattern": "warm",
      "evidence": [],
      "weight": 0.2,
      "validations": 0,
      "status": "pending_veto",
      "conditional": null,
      "category": "preference"
    },
    {
      "id": "hyp_1767072735_2",
      "created_ts": 1767072735.8780673,
      "pattern": "helpful",
      "evidence": [],
      "weight": 0.2,
      "validations": 0,
      "status": "pending_veto",
      "conditional": null,
      "category": "preference"
    },
    {
      "id": "hyp_1767072735_3",
      "created_ts": 1767072735.8780673,
      "pattern": "gentle",
      "evidence": [],
      "weight": 0.2,
      "validations": 0,
      "status": "pending_veto",
      "conditional": null,
      "category": "preference"
    },
    {
      "id": "hyp_1767072735_4",
      "created_ts": 1767072735.8780673,
      "pattern": "steady",
      "evidence": [],
      "weight": 0.2,
      "validations": 0,
      "status": "pending_veto",
      "conditional": null,
      "category": "preference"
    },
    {
      "id": "hyp_1767072737_0",
      "created_ts": 1767072737.54896,
      "pattern": "keep building",
      "evidence": [],
      "weight": 0.2,
      "validations": 0,
      "status": "pending_veto",
      "conditional": null,
      "category": "preference"
    },
    {
      "id": "hyp_1767072737_1",
      "created_ts": 1767072737.54896,
      "pattern": "warm",
      "evidence": [],
      "weight": 0.2,
      "validations": 0,
      "status": "pending_veto",
      "conditional": null,
      "category": "preference"
    },
    {
      "id": "hyp_1767072737_2",
      "created_ts": 1767072737.54896,
      "pattern": "helpful",
      "evidence": [],
      "weight": 0.2,
      "validations": 0,
      "status": "pending_veto",
      "conditional": null,
      "category": "preference"
    },
    {
      "id": "hyp_1767072737_3",
      "created_ts": 1767072737.54896,
      "pattern": "gentle",
      "evidence": [],
      "weight": 0.2,
      "validations": 0,
      "status": "pending_veto",
      "conditional": null,
      "category": "preference"
    },
    {
      "id": "hyp_1767072737_4",
      "created_ts": 1767072737.54896,
      "pattern": "steady",
      "evidence": [],
      "weight": 0.2,
      "validations": 0,
      "status": "pending_veto",
      "conditional": null,
      "category": "preference"
    },
    {
      "id": "hyp_1767072739_0",
      "created_ts": 1767072739.147274,
      "pattern": "keep building",
      "evidence": [],
      "weight": 0.2,
      "validations": 0,
      "status": "pending_veto",
      "conditional": null,
      "category": "preference"
    },
    {
      "id": "hyp_1767072739_1",
      "created_ts": 1767072739.147274,
      "pattern": "warm",
      "evidence": [],
      "weight": 0.2,
      "validations": 0,
      "status": "pending_veto",
      "conditional": null,
      "category": "preference"
    },
    {
      "id": "hyp_1767072739_2",
      "created_ts": 1767072739.147274,
      "pattern": "helpful",
      "evidence": [],
      "weight": 0.2,
      "validations": 0,
      "status": "pending_veto",
      "conditional": null,
      "category": "preference"
    },
    {
      "id": "hyp_1767072739_3",
      "created_ts": 1767072739.147274,
      "pattern": "gentle",
      "evidence": [],
      "weight": 0.2,
      "validations": 0,
      "status": "pending_veto",
      "conditional": null,
      "category": "preference"
    },
    {
      "id": "hyp_1767072739_4",
      "created_ts": 1767072739.147274,
      "pattern": "steady",
      "evidence": [],
      "weight": 0.2,
      "validations": 0,
      "status": "pending_veto",
      "conditional": null,
      "category": "preference"
    },
    {
      "id": "hyp_1767072740_0",
      "created_ts": 1767072740.751461,
      "pattern": "keep building",
      "evidence": [],
      "weight": 0.2,
      "validations": 0,
      "status": "pending_veto",
      "conditional": null,
      "category": "preference"
    },
    {
      "id": "hyp_1767072740_1",
      "created_ts": 1767072740.751461,
      "pattern": "warm",
      "evidence": [],
      "weight": 0.2,
      "validations": 0,
      "status": "pending_veto",
      "conditional": null,
      "category": "preference"
    },
    {
      "id": "hyp_1767072740_2",
      "created_ts": 1767072740.751461,
      "pattern": "helpful",
      "evidence": [],
      "weight": 0.2,
      "validations": 0,
      "status": "pending_veto",
      "conditional": null,
      "category": "preference"
    },
    {
      "id": "hyp_1767072740_3",
      "created_ts": 1767072740.751461,
      "pattern": "gentle",
      "evidence": [],
      "weight": 0.2,
      "validations": 0,
      "status": "pending_veto",
      "conditional": null,
      "category": "preference"
    },
    {
      "id": "hyp_1767072740_4",
      "created_ts": 1767072740.751461,
      "pattern": "steady",
      "evidence": [],
      "weight": 0.2,
      "validations": 0,
      "status": "pending_veto",
      "conditional": null,
      "category": "preference"
    },
    {
      "id": "hyp_1767072742_0",
      "created_ts": 1767072742.5127492,
      "pattern": "keep building",
      "evidence": [],
      "weight": 0.2,
      "validations": 0,
      "status": "pending_veto",
      "conditional": null,
      "category": "preference"
    },
    {
      "id": "hyp_1767072742_1",
      "created_ts": 1767072742.5127492,
      "pattern": "warm",
      "evidence": [],
      "weight": 0.2,
      "validations": 0,
      "status": "pending_veto",
      "conditional": null,
      "category": "preference"
    },
    {
      "id": "hyp_1767072742_2",
      "created_ts": 1767072742.5127492,
      "pattern": "helpful",
      "evidence": [],
      "weight": 0.2,
      "validations": 0,
      "status": "pending_veto",
      "conditional": null,
      "category": "preference"
    },
    {
      "id": "hyp_1767072742_3",
      "created_ts": 1767072742.5127492,
      "pattern": "gentle",
      "evidence": [],
      "weight": 0.2,
      "validations": 0,
      "status": "pending_veto",
      "conditional": null,
      "category": "preference"
    },
    {
      "id": "hyp_1767072742_4",
      "created_ts": 1767072742.5127492,
      "pattern": "steady",
      "evidence": [],
      "weight": 0.2,
      "validations": 0,
      "status": "pending_veto",
      "conditional": null,
      "category": "preference"
    },
    {
      "id": "hyp_1767072744_0",
      "created_ts": 1767072744.2588105,
      "pattern": "keep building",
      "evidence": [],
      "weight": 0.2,
      "validations": 0,
      "status": "pending_veto",
      "conditional": null,
      "category": "preference"
    },
    {
      "id": "hyp_1767072744_1",
      "created_ts": 1767072744.2588105,
      "pattern": "warm",
      "evidence": [],
      "weight": 0.2,
      "validations": 0,
      "status": "pending_veto",
      "conditional": null,
      "category": "preference"
    },
    {
      "id": "hyp_1767072744_2",
      "created_ts": 1767072744.2588105,
      "pattern": "helpful",
      "evidence": [],
      "weight": 0.2,
      "validations": 0,
      "status": "pending_veto",
      "conditional": null,
      "category": "preference"
    },
    {
      "id": "hyp_1767072744_3",
      "created_ts": 1767072744.2588105,
      "pattern": "gentle",
      "evidence": [],
      "weight": 0.2,
      "validations": 0,
      "status": "pending_veto",
      "conditional": null,
      "category": "preference"
    },
    {
      "id": "hyp_1767072744_4",
      "created_ts": 1767072744.2588105,
      "pattern": "steady",
      "evidence": [],
      "weight": 0.2,
      "validations": 0,
      "status": "pending_veto",
      "conditional": null,
      "category": "preference"
    },
    {
      "id": "hyp_1767072745_0",
      "created_ts": 1767072745.9549735,
      "pattern": "keep building",
      "evidence": [],
      "weight": 0.2,
      "validations": 0,
      "status": "pending_veto",
      "conditional": null,
      "category": "preference"
    },
    {
      "id": "hyp_1767072745_1",
      "created_ts": 1767072745.9549735,
      "pattern": "warm",
      "evidence": [],
      "weight": 0.2,
      "validations": 0,
      "status": "pending_veto",
      "conditional": null,
      "category": "preference"
    },
    {
      "id": "hyp_1767072745_2",
      "created_ts": 1767072745.9549735,
      "pattern": "helpful",
      "evidence": [],
      "weight": 0.2,
      "validations": 0,
      "status": "pending_veto",
      "conditional": null,
      "category": "preference"
    },
    {
      "id": "hyp_1767072745_3",
      "created_ts": 1767072745.9549735,
      "pattern": "gentle",
      "evidence": [],
      "weight": 0.2,
      "validations": 0,
      "status": "pending_veto",
      "conditional": null,
      "category": "preference"
    },
    {
      "id": "hyp_1767072745_4",
      "created_ts": 1767072745.9549735,
      "pattern": "steady",
      "evidence": [],
      "weight": 0.2,
      "validations": 0,
      "status": "pending_veto",
      "conditional": null,
      "category": "preference"
    },
    {
      "id": "hyp_1767072747_0",
      "created_ts": 1767072747.636885,
      "pattern": "keep building",
      "evidence": [],
      "weight": 0.2,
      "validations": 0,
      "status": "pending_veto",
      "conditional": null,
      "category": "preference"
    },
    {
      "id": "hyp_1767072747_1",
      "created_ts": 1767072747.636885,
      "pattern": "warm",
      "evidence": [],
      "weight": 0.2,
      "validations": 0,
      "status": "pending_veto",
      "conditional": null,
      "category": "preference"
    },
    {
      "id": "hyp_1767072747_2",
      "created_ts": 1767072747.636885,
      "pattern": "helpful",
      "evidence": [],
      "weight": 0.2,
      "validations": 0,
      "status": "pending_veto",
      "conditional": null,
      "category": "preference"
    },
    {
      "id": "hyp_1767072747_3",
      "created_ts": 1767072747.636885,
      "pattern": "gentle",
      "evidence": [],
      "weight": 0.2,
      "validations": 0,
      "status": "pending_veto",
      "conditional": null,
      "category": "preference"
    },
    {
      "id": "hyp_1767072747_4",
      "created_ts": 1767072747.636885,
      "pattern": "steady",
      "evidence": [],
      "weight": 0.2,
      "validations": 0,
      "status": "pending_veto",
      "conditional": null,
      "category": "preference"
    },
    {
      "id": "hyp_1767072750_0",
      "created_ts": 1767072750.671741,
      "pattern": "keep building",
      "evidence": [],
      "weight": 0.2,
      "validations": 0,
      "status": "pending_veto",
      "conditional": null,
      "category": "preference"
    },
    {
      "id": "hyp_1767072750_1",
      "created_ts": 1767072750.671741,
      "pattern": "warm",
      "evidence": [],
      "weight": 0.2,
      "validations": 0,
      "status": "pending_veto",
      "conditional": null,
      "category": "preference"
    },
    {
      "id": "hyp_1767072750_2",
      "created_ts": 1767072750.671741,
      "pattern": "helpful",
      "evidence": [],
      "weight": 0.2,
      "validations": 0,
      "status": "pending_veto",
      "conditional": null,
      "category": "preference"
    },
    {
      "id": "hyp_1767072750_3",
      "created_ts": 1767072750.671741,
      "pattern": "gentle",
      "evidence": [],
      "weight": 0.2,
      "validations": 0,
      "status": "pending_veto",
      "conditional": null,
      "category": "preference"
    },
    {
      "id": "hyp_1767072750_4",
      "created_ts": 1767072750.671741,
      "pattern": "steady",
      "evidence": [],
      "weight": 0.2,
      "validations": 0,
      "status": "pending_veto",
      "conditional": null,
      "category": "preference"
    },
    {
      "id": "hyp_1767072752_0",
      "created_ts": 1767072752.7321272,
      "pattern": "keep building",
      "evidence": [],
      "weight": 0.2,
      "validations": 0,
      "status": "pending_veto",
      "conditional": null,
      "category": "preference"
    },
    {
      "id": "hyp_1767072752_1",
      "created_ts": 1767072752.7321272,
      "pattern": "warm",
      "evidence": [],
      "weight": 0.2,
      "validations": 0,
      "status": "pending_veto",
      "conditional": null,
      "category": "preference"
    },
    {
      "id": "hyp_1767072752_2",
      "created_ts": 1767072752.7321272,
      "pattern": "helpful",
      "evidence": [],
      "weight": 0.2,
      "validations": 0,
      "status": "pending_veto",
      "conditional": null,
      "category": "preference"
    },
    {
      "id": "hyp_1767072752_3",
      "created_ts": 1767072752.7321272,
      "pattern": "gentle",
      "evidence": [],
      "weight": 0.2,
      "validations": 0,
      "status": "pending_veto",
      "conditional": null,
      "category": "preference"
    },
    {
      "id": "hyp_1767072752_4",
      "created_ts": 1767072752.7321272,
      "pattern": "steady",
      "evidence": [],
      "weight": 0.2,
      "validations": 0,
      "status": "pending_veto",
      "conditional": null,
      "category": "preference"
    },
    {
      "id": "hyp_1767072754_0",
      "created_ts": 1767072754.9235363,
      "pattern": "keep building",
      "evidence": [],
      "weight": 0.2,
      "validations": 0,
      "status": "pending_veto",
      "conditional": null,
      "category": "preference"
    },
    {
      "id": "hyp_1767072754_1",
      "created_ts": 1767072754.9235363,
      "pattern": "warm",
      "evidence": [],
      "weight": 0.2,
      "validations": 0,
      "status": "pending_veto",
      "conditional": null,
      "category": "preference"
    },
    {
      "id": "hyp_1767072754_2",
      "created_ts": 1767072754.9235363,
      "pattern": "helpful",
      "evidence": [],
      "weight": 0.2,
      "validations": 0,
      "status": "pending_veto",
      "conditional": null,
      "category": "preference"
    },
    {
      "id": "hyp_1767072754_3",
      "created_ts": 1767072754.9235363,
      "pattern": "gentle",
      "evidence": [],
      "weight": 0.2,
      "validations": 0,
      "status": "pending_veto",
      "conditional": null,
      "category": "preference"
    },
    {
      "id": "hyp_1767072754_4",
      "created_ts": 1767072754.9235363,
      "pattern": "steady",
      "evidence": [],
      "weight": 0.2,
      "validations": 0,
      "status": "pending_veto",
      "conditional": null,
      "category": "preference"
    }
  ],
  "pending_veto_queue": [
    "hyp_1767071599_0",
    "hyp_1767071599_1",
    "hyp_1767071599_2",
    "hyp_1767071599_3",
    "hyp_1767071599_4"
  ],
  "heritage_candidates": [],
  "rejected_archive": []
}